LICENSE.txt
MANIFEST.in
README.rst
setup.py
django_receipts/__init__.py
django_receipts/admin.py
django_receipts/constants.py
django_receipts/models.py
django_receipts/tasks.py
django_receipts/tests.py
django_receipts/urls.py
django_receipts/views.py
django_receipts.egg-info/PKG-INFO
django_receipts.egg-info/SOURCES.txt
django_receipts.egg-info/dependency_links.txt
django_receipts.egg-info/not-zip-safe
django_receipts.egg-info/requires.txt
django_receipts.egg-info/top_level.txt