Metadata-Version: 1.0
Name: django-receipts
Version: 0.1.5
Summary: Django app for verifying web app receipts
Home-page: https://github.com/andymckay/django-receipts
Author: Andy McKay
Author-email: andym@mozilla.com
License: BSD
Platform: UNKNOWN
Classifier: Intended Audience :: Developers
Classifier: Natural Language :: English
Classifier: Operating System :: OS Independent
